proxy_ninja_ng/__init__.py
proxy_ninja_ng-0.1.0.dist-info/LICENSE.md
proxy_ninja_ng-0.1.0.dist-info/METADATA
proxy_ninja_ng-0.1.0.dist-info/WHEEL
proxy_ninja_ng-0.1.0.dist-info/top_level.txt
proxy_ninja_ng-0.1.0.dist-info/RECORD
