Metadata-Version: 2.1
Name: proxy-ninja-ng
Version: 0.1.0
Summary: Python3 library for scraping http/https and socks(4/5) proxies.
Home-page: https://github.com/sc4rfurry/ProxyNinja-ng-PyPi
Author: sc4rfurry
Author-email: akalucifr@protonmail.ch
License: MIT
Keywords: proxy,free proxy,proxy grabber,http proxy,https proxy,socks proxy,socks4 proxy,socks5 proxy
Platform: UNKNOWN
Classifier: Development Status :: 5 - Production/Stable
Classifier: Intended Audience :: Education
Classifier: Operating System :: OS Independent
Classifier: License :: OSI Approved :: MIT License
Classifier: Programming Language :: Python :: 3
License-File: LICENSE.md
Requires-Dist: bs4
Requires-Dist: html5lib
Requires-Dist: rich
Requires-Dist: user-agent
